jrpybestprac/__init__.py
jrpybestprac/__version__.py
jrpybestprac/data/movies.zip
jrpybestprac/data/penguins.csv
jrpybestprac/data/taxis.csv
jrpybestprac/data.py
jrpybestprac/examples/script-dirty.py
jrpybestprac/examples/script-messy.py
jrpybestprac/examples/test_forecast.py
jrpybestprac/examples.py
jrpybestprac/resources.py
jrpybestprac-0.1.2.dist-info/METADATA
jrpybestprac-0.1.2.dist-info/WHEEL
jrpybestprac-0.1.2.dist-info/RECORD
