Metadata-Version: 2.1
Name: jrpybestprac
Version: 0.1.2
Summary: Jumping Rivers: Python Best Practices
Author: Jumping Rivers
Author-email: info@jumpingrivers.com
Requires-Python: >=3.8,<4.0
Classifier: Programming Language :: Python :: 3
Classifier: Programming Language :: Python :: 3.8
Classifier: Programming Language :: Python :: 3.9
Classifier: Programming Language :: Python :: 3.10
Classifier: Programming Language :: Python :: 3.11
Requires-Dist: black (>=22.1)
Requires-Dist: matplotlib (>=3.0)
Requires-Dist: pandas (>=1)
Requires-Dist: pep8-naming (>=0.12)
Requires-Dist: pyjanitor (<0.23)
Requires-Dist: reprexpy (<=1)
Requires-Dist: seaborn (>=0.11)
